odoo8_addon_account_payment_term_multi_day-8.0.1.0.0.99.dev12-py3.8-nspkg.pth
odoo_addons/account_payment_term_multi_day/README.rst
odoo_addons/account_payment_term_multi_day/__init__.py
odoo_addons/account_payment_term_multi_day/__openerp__.py
odoo_addons/account_payment_term_multi_day/i18n/account_payment_term_multi_day.pot
odoo_addons/account_payment_term_multi_day/i18n/de.po
odoo_addons/account_payment_term_multi_day/i18n/es.po
odoo_addons/account_payment_term_multi_day/i18n/it.po
odoo_addons/account_payment_term_multi_day/i18n/nl_NL.po
odoo_addons/account_payment_term_multi_day/i18n/pt_BR.po
odoo_addons/account_payment_term_multi_day/i18n/sl.po
odoo_addons/account_payment_term_multi_day/i18n/tr_TR.po
odoo_addons/account_payment_term_multi_day/migrations/8.0.1.0.0/post-migration.py
odoo_addons/account_payment_term_multi_day/models/__init__.py
odoo_addons/account_payment_term_multi_day/models/account_payment_term.py
odoo_addons/account_payment_term_multi_day/static/description/icon.png
odoo_addons/account_payment_term_multi_day/static/description/icon.svg
odoo_addons/account_payment_term_multi_day/tests/__init__.py
odoo_addons/account_payment_term_multi_day/tests/test_account_payment_term_multi_day.py
odoo_addons/account_payment_term_multi_day/views/account_payment_term_view.xml
odoo8_addon_account_payment_term_multi_day-8.0.1.0.0.99.dev12.dist-info/METADATA
odoo8_addon_account_payment_term_multi_day-8.0.1.0.0.99.dev12.dist-info/WHEEL
odoo8_addon_account_payment_term_multi_day-8.0.1.0.0.99.dev12.dist-info/namespace_packages.txt
odoo8_addon_account_payment_term_multi_day-8.0.1.0.0.99.dev12.dist-info/top_level.txt
odoo8_addon_account_payment_term_multi_day-8.0.1.0.0.99.dev12.dist-info/RECORD
